discord/ext/autoreload/__init__.py
discord/ext/autoreload/reloader.py
discord_ext_autoreload-0.1.0.dist-info/LICENSE
discord_ext_autoreload-0.1.0.dist-info/METADATA
discord_ext_autoreload-0.1.0.dist-info/WHEEL
discord_ext_autoreload-0.1.0.dist-info/top_level.txt
discord_ext_autoreload-0.1.0.dist-info/RECORD
